nuaabook/__init__.py
nuaabook-1.0.0.dist-info/METADATA
nuaabook-1.0.0.dist-info/WHEEL
nuaabook-1.0.0.dist-info/top_level.txt
nuaabook-1.0.0.dist-info/RECORD
