Metadata-Version: 2.1
Name: nuaabook
Version: 1.0.0
Summary: 南航图书馆电子书下载
Home-page: https://www.suruifu.com/
Author: Ryan Su
Author-email: i@suruifu.com
License: UNKNOWN
Platform: UNKNOWN
Requires-Dist: requests
Requires-Dist: reportlab
